async_execution_da/__init__.py
async_execution_da/api_layer/__init__.py
async_execution_da/api_layer/future_api.py
async_execution_da/base_api/__init__.py
async_execution_da/base_api/future_demo.py
async_execution_da/models/__init__.py
async_execution_da/models/capital_info.py
async_execution_da/models/order_book.py
async_execution_da/models/trade_book.py
async_execution_da/models/trade_record.py
async_execution_da/utils/__init__.py
async_execution_da/utils/time_utils.py
async_execution_da-0.1.0.dist-info/licenses/LICENSE
async_execution_da-0.1.0.dist-info/METADATA
async_execution_da-0.1.0.dist-info/WHEEL
async_execution_da-0.1.0.dist-info/top_level.txt
async_execution_da-0.1.0.dist-info/RECORD
