Metadata-Version: 2.4
Name: async-execution-da
Version: 0.1.0
Summary: Async execution layer for futures trading built on a broker SDK.
Author: Yuwen Lu
License: MIT
Project-URL: Homepage, https://github.com/Reece-Lu/async-execution-da
Project-URL: Repository, https://github.com/Reece-Lu/async-execution-da
Classifier: License :: OSI Approved :: MIT License
Classifier: Programming Language :: Python :: 3
Classifier: Programming Language :: Python :: 3.10
Classifier: Programming Language :: Python :: 3 :: Only
Classifier: Intended Audience :: Developers
Classifier: Topic :: Office/Business :: Financial
Classifier: Topic :: Software Development :: Libraries
Requires-Python: <3.11,>=3.10
License-File: LICENSE
Dynamic: license-file
